<oai_dc:dc xmlns:oai_dc="http://www.openarchives.org/OAI/2.0/oai_dc/" xmlns:dc="http://purl.org/dc/elements/1.1/" xmlns:xsi="http://www.w3.org/2001/XMLSchema-instance" xmlns="http://www.openarchives.org/OAI/2.0/" xsi:schemaLocation="http://www.openarchives.org/OAI/2.0/oai_dc/ http://www.openarchives.org/OAI/2.0/oai_dc.xsd">
<dc:title>Wesley Lester Bandy copyprint photograph</dc:title>
<dc:description>Pvt. Wesley Lester Bandy, Co. E 1st Tenn. Mtd. Inf. Regt., USA, was born on March 7, 1838, in Smith County, Tenn. He was the son of Lewis Bandy. He served in the 1st from Jan. 16, 1864, to Jan. 23, 1865. He then served as 2nd Lt. in Co. D, 8th Tenn. Mtd. Inf., USA, from Feb. 10, 1865, until Aug. 31, 1865. Wesley had seven brothers who also fought in the Civil War, including Pvt. Yancy D. Bandy, Co. K and C, 9th Ky. Inf., USA, who died during the war. Wesley is buried in Underwood Cemetery in Macon County.</dc:description>
<dc:date>approximately 1915</dc:date>
<dc:subject>Bandy, Wesley Lester </dc:subject>
<dc:coverage>Macon County (Tenn.)</dc:coverage>
<dc:source>Lafayette, Macon County, Tennessee</dc:source>
<dc:identifier>lafa053</dc:identifier>
<dc:type>Still Image</dc:type>
<dc:format>Image/jpeg</dc:format>
<dc:format>Photographs; Prints</dc:format>
<dc:rights>No copyright - United States: http://rightsstatements.org/vocab/NoC-US/1.0/</dc:rights>
<dc:identifier>http://cdm15138.contentdm.oclc.org/cdm/ref/collection/p15138coll6/id/11704</dc:identifier></oai_dc:dc>