<oai_dc:dc xmlns:oai_dc="http://www.openarchives.org/OAI/2.0/oai_dc/" xmlns:dc="http://purl.org/dc/elements/1.1/" xmlns:xsi="http://www.w3.org/2001/XMLSchema-instance" xmlns="http://www.openarchives.org/OAI/2.0/" xsi:schemaLocation="http://www.openarchives.org/OAI/2.0/oai_dc/ http://www.openarchives.org/OAI/2.0/oai_dc.xsd">
<dc:title>Civil War diary of William Raleigh (or Riley) Clack, Co. B, 43rd Tenn. Inf. Regt., CSA</dc:title>
<dc:description>Company B, 43rd Tenn. Inf. Regt., CSA was raised in Sulphur Springs, Rhea County, Tenn. The diary begins on May 23, 1863 about the time that the regiment reported to the defenses of Vicksburg, Mississippi and ends on July 28, 1863. Vicksburg surrendered July 4, 1863 and Clack mentions the surrender in the diary. Paroled with the rest of his regiment after the surrender, Clack took the oath of allegiance in December 1863 and presumably returned home to Rhea County, Tennessee.</dc:description>
<dc:date>1863</dc:date>
<dc:coverage>Vicksburg (Miss.)</dc:coverage>
<dc:source>Dayton, Rhea County, Tennessee</dc:source>
<dc:identifier>rhea043</dc:identifier>
<dc:type>Text; No</dc:type>
<dc:format>Image/jpeg</dc:format>
<dc:format>Diaries</dc:format>
<dc:rights>No copyright - United States: http://rightsstatements.org/vocab/NoC-US/1.0/</dc:rights>
<dc:identifier>http://cdm15138.contentdm.oclc.org/cdm/ref/collection/p15138coll6/id/12037</dc:identifier></oai_dc:dc>