<oai_dc:dc xmlns:oai_dc="http://www.openarchives.org/OAI/2.0/oai_dc/" xmlns:dc="http://purl.org/dc/elements/1.1/" xmlns:xsi="http://www.w3.org/2001/XMLSchema-instance" xmlns="http://www.openarchives.org/OAI/2.0/" xsi:schemaLocation="http://www.openarchives.org/OAI/2.0/oai_dc/ http://www.openarchives.org/OAI/2.0/oai_dc.xsd">
<dc:title>French. Lizzie Crozier French Scrapbook, p. 07 d</dc:title>
<dc:description>Lizzie Crozier French Scrapbook, p. 07 d. Newspaper clipping: 'Knoxville's Lady Senator.' Knoxville Journal Tribune.  December 31, 1922. Includes photograph of James and Lizzie Crozier, cut by Knoxville Engraving Co.</dc:description>
<dc:subject>Clippings; Scrapbooks; Women; Portraits; Children;</dc:subject>
<dc:publisher>Knoxville Journal Tribune</dc:publisher>
<dc:date>December 31, 1922</dc:date>
<dc:type>scrapbook</dc:type>
<dc:format>400 dpi, TIFF</dc:format>
<dc:identifier>Lizzie Crozier French Scrapbook, p. 07</dc:identifier>
<dc:source>C.M. McClung Historical Collection, Knox County Public Library</dc:source>
<dc:rights>For information on license and use fees and acquiring high-resolution image files, contact DigitalCollections@knoxlib.org or phone 865 215-8814. Please provide a brief description of the material.</dc:rights>
<dc:description>KNOXVILLE'S LADY SENATOR
Little Lizzie Crozier (Mrs. L. Crozier French) and her brother James, as they appeared  several  years ago.    Mrs.   French  is one of   Knoxville's most
 prominent clubwomen  and received   the endorsement of practically all clubs for a 
seat in the United States senate in event a vacancy should (missing)

</dc:description>
<dc:identifier>http://cdm16311.contentdm.oclc.org/cdm/ref/collection/p265301coll8/id/268</dc:identifier></oai_dc:dc>