<oai_dc:dc xmlns:oai_dc="http://www.openarchives.org/OAI/2.0/oai_dc/" xmlns:dc="http://purl.org/dc/elements/1.1/" xmlns:xsi="http://www.w3.org/2001/XMLSchema-instance" xmlns="http://www.openarchives.org/OAI/2.0/" xsi:schemaLocation="http://www.openarchives.org/OAI/2.0/oai_dc/ http://www.openarchives.org/OAI/2.0/oai_dc.xsd">
<dc:title>French. Lizzie Crozier French Scrapbook, p. 37f</dc:title>
<dc:description>Lizzie Crozier French Scrapbook, p. 37 f. Newspaper clipping:  fragment: Did he do it?  (The 65th Congress met from March 4, 1917 to March 4, 1919). (continued on p. 37 g)</dc:description>
<dc:subject>Politics &amp; government; Clippings; Scrapbooks; Women; Women's suffrage;</dc:subject>
<dc:creator>[Mrs. Mary L. McLendon]</dc:creator>
<dc:date>Unknown</dc:date>
<dc:type>scrapbook</dc:type>
<dc:format>400 dpi, TIFF</dc:format>
<dc:identifier>Lizzie Crozier French Scrapbook p. 37</dc:identifier>
<dc:source>C.M. McClung Historical Collection, Knox County Public Library</dc:source>
<dc:rights>For information on license and use fees and acquiring high-resolution image files, contact DigitalCollections@knoxlib.org or phone 865 215-8814. Please provide a brief description of the material.</dc:rights>
<dc:description>Did he do  it?
Has anybody ever heard of his
making an effort to eliminate the
15th Federal amendment? Women
would like to know if he ever did.
"Hoke and Tom" always voted
against   the   Susan B.     Anthony
amendment whenever it "bobbed up
secretly" in the 65th congress, and
then   what   happened?
Tom Hardwick was left at home
by his constituents who were all
men, and Wm. J. Harris is now the
junior senator. Wm. Schley Howard
who voted against the woman suffrage   amendment   in   the   65th   con- (missing)</dc:description>
<dc:identifier>http://cdm16311.contentdm.oclc.org/cdm/ref/collection/p265301coll8/id/489</dc:identifier></oai_dc:dc>