<oai_qdc:qualifieddc xmlns:oai_qdc="http://worldcat.org/xmlschemas/qdc-1.0/" xmlns:dc="http://purl.org/dc/elements/1.1/" xmlns:dcterms="http://purl.org/dc/terms/" xmlns:xsi="http://www.w3.org/2001/XMLSchema-instance" xmlns="http://www.openarchives.org/OAI/2.0/" xsi:schemaLocation="http://worldcat.org/xmlschemas/qdc-1.0/ http://worldcat.org/xmlschemas/qdc/1.0/qdc-1.0.xsd http://purl.org/net/oclcterms http://worldcat.org/xmlschemas/oclcterms/1.4/oclcterms-1.4.xsd">
<dc:title>Lithograph of James K. Polk, eleventh president of the United States</dc:title>
<dc:description>A colored lithograph of James K. Polk. His portrait is in the middle of a circle with stars on it. The background is decorated with flags and eagles.</dc:description>
<dc:description>James Knox Polk was born on November 2, 1795 in Pineville, North Carolina and moved to Tennessee to study law. Over time, he was elected to the Tennessee legislature and eventually to the United States House of Representatives in 1825. From 1835 to 1839, Polk served as the Speaker of the House of Representatives. In 1839, Polk left Congress to serve as the Governor of Tennessee. In 1844, Polk became the eleventh president of the United States. During his presidency, the United States expanded significantly with the annexation of the Republic of Texas, the Oregon Treaty, and the conclusion of the Mexican-American War. Polk died on June 15, 1849.</dc:description>
<dc:date>1846</dc:date>
<dc:publisher>Currier, N.</dc:publisher>
<dcterms:references>New York (N.Y.)</dcterms:references>
<dc:source>Library Photograph Collection, Oversize</dc:source>
<dcterms:instructionalMethod>4.63; 8.61; James K. Polk; Growth of the Republic</dcterms:instructionalMethod>
<dc:subject>Polk, James Knox, --1795 - 1849; Presidents</dc:subject>
<dc:subject>Lithographs</dc:subject>
<dc:source>Tennessee State Library and Archives</dc:source>
<dc:identifier>32205</dc:identifier>
<dc:source>Library Oversize, Drawer 28</dc:source>
<dcterms:isPartOf>James K. Polk Collection;</dcterms:isPartOf>
<dc:type>Still Image</dc:type>
<dc:format>Images/jpeg</dc:format>
<dcterms:medium>Lithographs; Prints</dcterms:medium>
<dc:rights>No copyright - United States: http://rightsstatements.org/vocab/NoC-US/1.0/</dc:rights>
<dc:identifier>http://cdm15138.contentdm.oclc.org/cdm/ref/collection/p15138coll43/id/3</dc:identifier></oai_qdc:qualifieddc>