<oai_dc:dc xmlns:oai_dc="http://www.openarchives.org/OAI/2.0/oai_dc/" xmlns:dc="http://purl.org/dc/elements/1.1/" xmlns:xsi="http://www.w3.org/2001/XMLSchema-instance" xmlns="http://www.openarchives.org/OAI/2.0/" xsi:schemaLocation="http://www.openarchives.org/OAI/2.0/oai_dc/ http://www.openarchives.org/OAI/2.0/oai_dc.xsd">
<dc:title>Lowenstein House</dc:title>
<dc:date>1928</dc:date>
<dc:subject>Claiming Space</dc:subject>
<dc:subject>Business Districts</dc:subject>
<dc:subject>Dwellings; Historic buildings</dc:subject>
<dc:coverage>United States -- Tennessee -- Memphis</dc:coverage>
<dc:coverage>Shelby County</dc:coverage>
<dc:description>Two-and-one half story brick house with stone-arched center entry and an open arched wrap-around front porch on right. The house features a  tower cupola, echoed by a decorative dormer window below on the left side, a pyramid roofline with cross gable dormers, several chimneys, a stained glass fan light window and a pierced stone rose window.</dc:description>
<dc:description>Elias Lowenstein's handsome 1891 home is representative of the wide array of fine Victorian houses built by wealthy Memphians in the prosperous decades before and after the American Civil War.</dc:description>
<dc:type>Still image</dc:type>
<dc:format>jpeg</dc:format>
<dc:format>Photograph</dc:format>
<dc:publisher>Center for Southern Folklore</dc:publisher>
<dc:relation>Courtesy of Center for Southern Folklore</dc:relation>
<dc:rights>Reproduction permitted for non-profit educational and research purposes only. All reproductions require acknowledgement of the contributing institution. For research inquiries about specific objects, contact the Center for Southern Folklore.</dc:rights>
<dc:publisher>Digital Initiatives, James E. Walker Library, Middle Tennessee State University</dc:publisher>
<dc:identifier>http://cdm15838.contentdm.oclc.org/cdm/ref/collection/p15838coll7/id/256</dc:identifier></oai_dc:dc>